<annotation>
	<folder>training</folder>
	<filename>	(2340).jpg</filename>
	<path>C:\Users\karto\Downloads\vespula germanica - Búsqueda_de_Google\training\	(2340).jpg</path>
	<source>
		<database>Unknown</database>
	</source>
	<size>
		<width>800</width>
		<height>600</height>
		<depth>3</depth>
	</size>
	<segmented>0</segmented>
	<object>
		<name>abeja</name>
		<pose>Unspecified</pose>
		<truncated>0</truncated>
		<difficult>0</difficult>
		<bndbox>
			<xmin>225</xmin>
			<ymin>397</ymin>
			<xmax>406</xmax>
			<ymax>590</ymax>
		</bndbox>
	</object>
	<object>
		<name>abeja</name>
		<pose>Unspecified</pose>
		<truncated>0</truncated>
		<difficult>0</difficult>
		<bndbox>
			<xmin>479</xmin>
			<ymin>386</ymin>
			<xmax>714</xmax>
			<ymax>581</ymax>
		</bndbox>
	</object>
	<object>
		<name>abeja</name>
		<pose>Unspecified</pose>
		<truncated>0</truncated>
		<difficult>0</difficult>
		<bndbox>
			<xmin>81</xmin>
			<ymin>361</ymin>
			<xmax>325</xmax>
			<ymax>561</ymax>
		</bndbox>
	</object>
	<object>
		<name>abeja</name>
		<pose>Unspecified</pose>
		<truncated>1</truncated>
		<difficult>0</difficult>
		<bndbox>
			<xmin>1</xmin>
			<ymin>254</ymin>
			<xmax>290</xmax>
			<ymax>386</ymax>
		</bndbox>
	</object>
	<object>
		<name>abeja</name>
		<pose>Unspecified</pose>
		<truncated>0</truncated>
		<difficult>0</difficult>
		<bndbox>
			<xmin>372</xmin>
			<ymin>90</ymin>
			<xmax>626</xmax>
			<ymax>242</ymax>
		</bndbox>
	</object>
	<object>
		<name>abeja</name>
		<pose>Unspecified</pose>
		<truncated>0</truncated>
		<difficult>0</difficult>
		<bndbox>
			<xmin>205</xmin>
			<ymin>10</ymin>
			<xmax>418</xmax>
			<ymax>214</ymax>
		</bndbox>
	</object>
	<object>
		<name>abeja</name>
		<pose>Unspecified</pose>
		<truncated>1</truncated>
		<difficult>0</difficult>
		<bndbox>
			<xmin>462</xmin>
			<ymin>484</ymin>
			<xmax>572</xmax>
			<ymax>600</ymax>
		</bndbox>
	</object>
	<object>
		<name>abeja</name>
		<pose>Unspecified</pose>
		<truncated>0</truncated>
		<difficult>0</difficult>
		<bndbox>
			<xmin>490</xmin>
			<ymin>286</ymin>
			<xmax>789</xmax>
			<ymax>434</ymax>
		</bndbox>
	</object>
</annotation>
