<annotation>
	<folder>training</folder>
	<filename>	(593).jpg</filename>
	<path>C:\Users\karto\Downloads\vespula germanica - Búsqueda_de_Google\training\	(593).jpg</path>
	<source>
		<database>Unknown</database>
	</source>
	<size>
		<width>800</width>
		<height>600</height>
		<depth>3</depth>
	</size>
	<segmented>0</segmented>
	<object>
		<name>chax</name>
		<pose>Unspecified</pose>
		<truncated>0</truncated>
		<difficult>0</difficult>
		<bndbox>
			<xmin>32</xmin>
			<ymin>22</ymin>
			<xmax>223</xmax>
			<ymax>350</ymax>
		</bndbox>
	</object>
	<object>
		<name>chax</name>
		<pose>Unspecified</pose>
		<truncated>0</truncated>
		<difficult>0</difficult>
		<bndbox>
			<xmin>186</xmin>
			<ymin>272</ymin>
			<xmax>446</xmax>
			<ymax>454</ymax>
		</bndbox>
	</object>
	<object>
		<name>chax</name>
		<pose>Unspecified</pose>
		<truncated>1</truncated>
		<difficult>0</difficult>
		<bndbox>
			<xmin>1</xmin>
			<ymin>341</ymin>
			<xmax>198</xmax>
			<ymax>488</ymax>
		</bndbox>
	</object>
	<object>
		<name>chax</name>
		<pose>Unspecified</pose>
		<truncated>1</truncated>
		<difficult>0</difficult>
		<bndbox>
			<xmin>560</xmin>
			<ymin>254</ymin>
			<xmax>800</xmax>
			<ymax>578</ymax>
		</bndbox>
	</object>
	<object>
		<name>chax</name>
		<pose>Unspecified</pose>
		<truncated>0</truncated>
		<difficult>0</difficult>
		<bndbox>
			<xmin>396</xmin>
			<ymin>134</ymin>
			<xmax>600</xmax>
			<ymax>328</ymax>
		</bndbox>
	</object>
	<object>
		<name>chax</name>
		<pose>Unspecified</pose>
		<truncated>1</truncated>
		<difficult>0</difficult>
		<bndbox>
			<xmin>650</xmin>
			<ymin>179</ymin>
			<xmax>800</xmax>
			<ymax>299</ymax>
		</bndbox>
	</object>
	<object>
		<name>chax</name>
		<pose>Unspecified</pose>
		<truncated>0</truncated>
		<difficult>0</difficult>
		<bndbox>
			<xmin>542</xmin>
			<ymin>4</ymin>
			<xmax>709</xmax>
			<ymax>250</ymax>
		</bndbox>
	</object>
	<object>
		<name>chax</name>
		<pose>Unspecified</pose>
		<truncated>0</truncated>
		<difficult>0</difficult>
		<bndbox>
			<xmin>330</xmin>
			<ymin>7</ymin>
			<xmax>618</xmax>
			<ymax>199</ymax>
		</bndbox>
	</object>
</annotation>
